garlic_validator/__init__.py
garlic_validator/__version__.py
garlic_validator/validator.py
garlic_validator-1.0.1.dist-info/LICENCE.txt
garlic_validator-1.0.1.dist-info/METADATA
garlic_validator-1.0.1.dist-info/WHEEL
garlic_validator-1.0.1.dist-info/top_level.txt
garlic_validator-1.0.1.dist-info/RECORD
