Metadata-Version: 2.1
Name: garlic-validator
Version: 1.0.1
Summary: Cerberus and validator-collection based custom validator package (garlic_validator) for python projects.
Home-page: https://github.com/bybatkhuu/python_validator
Download-URL: https://github.com/bybatkhuu/python_validator/archive/v1.0.1.tar.gz
Author: Batkhuu Byambajav
Author-email: batkhuu10@gmail.com
License: MIT
Keywords: garlic_validator,validator,validators,validate,validation,data-validation,Cerberus,validator-collection,custom-validator
Classifier: Development Status :: 3 - Alpha
Classifier: Intended Audience :: Developers
Classifier: Topic :: Software Development :: Build Tools
Classifier: License :: OSI Approved :: MIT License
Classifier: Programming Language :: Python :: 3.6
Classifier: Programming Language :: Python :: 3.7
Classifier: Programming Language :: Python :: 3.8
Classifier: Programming Language :: Python :: 3.9
Classifier: Programming Language :: Python :: 3.10
License-File: LICENCE.txt
Requires-Dist: Cerberus (>=1.3.4)
Requires-Dist: pydantic (>=1.9.1)
Requires-Dist: importlib-metadata (>=4.12.0)
Requires-Dist: jsonschema (>=4.6.0)
Requires-Dist: validator-collection (>=1.5.0)
